ycimpute/__init__.py
ycimpute/esemble/__init__.py
ycimpute/esemble/random_forest.py
ycimpute/imputer/__init__.py
ycimpute/imputer/expectation_maximization.py
ycimpute/imputer/gain.py
ycimpute/imputer/iterforest.py
ycimpute/imputer/knnimput.py
ycimpute/imputer/mice.py
ycimpute/imputer/mida.py
ycimpute/nn/__init__.py
ycimpute/nn/autoencoder.py
ycimpute/nn/gainnets.py
ycimpute/tree/__init__.py
ycimpute/tree/tree.py
ycimpute/unsupervised/__init__.py
ycimpute/unsupervised/knn/__init__.py
ycimpute/unsupervised/knn/argpartition.py
ycimpute/unsupervised/knn/common.py
ycimpute/unsupervised/knn/few_observed_entries.py
ycimpute/unsupervised/knn/normalized_distance.py
ycimpute/unsupervised/knn/optimistic.py
ycimpute/unsupervised/knn/reference.py
ycimpute/utils/__init__.py
ycimpute/utils/evaluate.py
ycimpute/utils/normalizer.py
ycimpute/utils/tools.py
ycimpute/utils/evaluator/__init__.py
ycimpute/utils/evaluator/evaluate_em.py
ycimpute/utils/shower/__init__.py
ycimpute/utils/shower/show.py
ycimpute/utils/shower/test_show.py
ycimpute-0.2.dist-info/LICENSE
ycimpute-0.2.dist-info/METADATA
ycimpute-0.2.dist-info/WHEEL
ycimpute-0.2.dist-info/top_level.txt
ycimpute-0.2.dist-info/RECORD
