Metadata-Version: 2.1
Name: ycimpute
Version: 0.2
Summary: Matrix completion and feature imputation algorithms
Home-page: https://github.com/OpenIDEA-YunanUniversity/ycimpute
Author: zhouyc
Author-email: yuanchenzhouhcmy@gmail.com
License: http://www.apache.org/licenses/LICENSE-2.0.html
Platform: UNKNOWN
Classifier: Development Status :: 3 - Alpha
Classifier: Environment :: Console
Classifier: Operating System :: OS Independent
Classifier: Intended Audience :: Science/Research
Classifier: License :: OSI Approved :: Apache Software License
Classifier: Programming Language :: Python
Classifier: Topic :: Communications
Requires-Dist: six
Requires-Dist: numpy (>=1.10)
Requires-Dist: scipy
Requires-Dist: scikit-learn (>=0.17.1)
Requires-Dist: torch (>=1.1.0)
